[
  {
    "ContainingType": "OnlineStore.WebApi.Controllers.OrderController",
    "Method": "BuyProduct",
    "RelativePath": "api/Order",
    "HttpMethod": "POST",
    "IsController": true,
    "Order": 0,
    "Parameters": [
      {
        "Name": "productId",
        "Type": "System.Int32",
        "IsRequired": false
      },
      {
        "Name": "userId",
        "Type": "System.Int32",
        "IsRequired": false
      }
    ],
    "ReturnTypes": []
  },
  {
    "ContainingType": "OnlineStore.WebApi.Controllers.ProductController",
    "Method": "AddProduct",
    "RelativePath": "api/Product",
    "HttpMethod": "POST",
    "IsController": true,
    "Order": 0,
    "Parameters": [
      {
        "Name": "product",
        "Type": "OnlineStore.Application.Dtos.ProductDto",
        "IsRequired": true
      }
    ],
    "ReturnTypes": []
  },
  {
    "ContainingType": "OnlineStore.WebApi.Controllers.ProductController",
    "Method": "Update",
    "RelativePath": "api/Product",
    "HttpMethod": "PUT",
    "IsController": true,
    "Order": 0,
    "Parameters": [
      {
        "Name": "id",
        "Type": "System.Int32",
        "IsRequired": false
      },
      {
        "Name": "inventoryCount",
        "Type": "System.Int32",
        "IsRequired": false
      }
    ],
    "ReturnTypes": []
  },
  {
    "ContainingType": "OnlineStore.WebApi.Controllers.ProductController",
    "Method": "GetProduct",
    "RelativePath": "api/Product/{id}",
    "HttpMethod": "GET",
    "IsController": true,
    "Order": 0,
    "Parameters": [
      {
        "Name": "id",
        "Type": "System.Int32",
        "IsRequired": true
      }
    ],
    "ReturnTypes": []
  }
]